{
  "code": "DMG-RWE-0",
  "slug": "beckybecky125-1",
  "contributor": "beckybecky125",
  "index": 1,
  "shell": {
    "code": "DMG-RW-USA-1",
    "stamp": "00"
  },
  "board": {
    "label": "DMG-BEAN-02",
    "circled_letters": "I",
    "panel_position": "6",
    "year": 1996,
    "month": 7,
    "u1": {
      "label": "DMG-RWE-0 S LH532MVP JAPAN D1 9630 E"
    },
    "u2": {
      "label": "DMG MBC1-B Nintendo P 6'69"
    }
  },
  "dump": {
    "tool": "GBxCart RW v1.4a/b/c",
    "log": "= FlashGBX Dump Report =\r\n\r\n== File Information ==\r\n* File Name:       Mega Man - Dr. Wily's Revenge (USA).gb\r\n* File Size:       256.0 KiB (262144 bytes)\r\n* CRC32:           47e70e08\r\n* MD5:             4ba4398181d98958fa7434ba7716f11a\r\n* SHA-1:           277edb3c844e812ba4b3eb9a96c9c30414541858\r\n* SHA-256:         33d16365318411f063edd9100c79458aabb7ea71bb1873e30f38b93814f0ec6e\r\n\r\n== General Information ==\r\n* Hardware:        GBxCart RW v1.4a/b/c – Firmware R42+L14\r\n* Software:        FlashGBX v4.5\r\n* OS Platform:     Windows-10-10.0.26100-SP0\r\n* Baud Rate:       1000000\r\n* Dump Time:       2026-01-20T14:43:06-08:00\r\n* Time Elapsed:    2 seconds (87.75 KiB/s)\r\n* Transfer Buffer: 4096 bytes\r\n* Retries:         0\r\n\r\n== Dumping Settings ==\r\n* Mode:            Game Boy\r\n* ROM Size:        256 KiB\r\n* Mapper Type:     MBC1\r\n* Cartridge Type:  Generic ROM Cartridge\r\n* Read Method:     A15\r\n\r\n== Parsed Data ==\r\n* Game Title:      MEGAMAN\r\n* Revision:        0\r\n* Super Game Boy:  No support\r\n* Game Boy Color:  No support\r\n* Nintendo Logo:   OK\r\n* Header Checksum: OK (0xE4)\r\n* ROM Checksum:    OK (0xC25B)\r\n* ROM Size:        256 KiB (0x03)\r\n* SRAM Size:       No SRAM (0x00)\r\n* Mapper Type:     MBC1 (0x01)\r\n* Target Platform: Game Boy\r\n\r\n== Database Match ==\r\n* Game Name:       Mega Man - Dr. Wily's Revenge (USA)\r\n* Region:          USA\r\n* Language(s):     En\r\n* Game Code:       DMG-RWE\r\n* ROM CRC32:       47e70e08\r\n* ROM Size:        256 KiB",
    "date": "2026-01-20",
    "crc32": "47e70e08",
    "md5": "4ba4398181d98958fa7434ba7716f11a",
    "sha1": "277edb3c844e812ba4b3eb9a96c9c30414541858",
    "sha256": "33d16365318411f063edd9100c79458aabb7ea71bb1873e30f38b93814f0ec6e"
  }
}